MCC_Linux_driver/__init__.py
MCC_Linux_driver/Bluetooth/__init__.py
MCC_Linux_driver/Bluetooth/bth_1208LS.py
MCC_Linux_driver/Bluetooth/mccBluetooth.py
MCC_Linux_driver/Ethernet/E_1608.py
MCC_Linux_driver/Ethernet/E_DIO24.py
MCC_Linux_driver/Ethernet/E_TC.py
MCC_Linux_driver/Ethernet/E_TC32.py
MCC_Linux_driver/Ethernet/__init__.py
MCC_Linux_driver/Ethernet/mccEthernet.py
MCC_Linux_driver/USB/__init__.py
MCC_Linux_driver/USB/bth_1208LS.py
MCC_Linux_driver/USB/mccUSB.py
MCC_Linux_driver/USB/thermocouple.py
MCC_Linux_driver/USB/usb_1208FS.py
MCC_Linux_driver/USB/usb_1208FS_Plus.py
MCC_Linux_driver/USB/usb_1208HS.py
MCC_Linux_driver/USB/usb_1208HS_rbf.py
MCC_Linux_driver/USB/usb_1208LS.py
MCC_Linux_driver/USB/usb_1408FS.py
MCC_Linux_driver/USB/usb_1408FS_Plus.py
MCC_Linux_driver/USB/usb_1608FS.py
MCC_Linux_driver/USB/usb_1608FS_Plus.py
MCC_Linux_driver/USB/usb_1608G.py
MCC_Linux_driver/USB/usb_1608G_rbf.py
MCC_Linux_driver/USB/usb_1608G_v1_rbf.py
MCC_Linux_driver/USB/usb_1616FS.py
MCC_Linux_driver/USB/usb_1808.py
MCC_Linux_driver/USB/usb_1808_rbf.py
MCC_Linux_driver/USB/usb_2001TC.py
MCC_Linux_driver/USB/usb_2020.py
MCC_Linux_driver/USB/usb_2020_rbf.py
MCC_Linux_driver/USB/usb_20x.py
MCC_Linux_driver/USB/usb_2400.py
MCC_Linux_driver/USB/usb_2600.py
MCC_Linux_driver/USB/usb_2600_rbf.py
MCC_Linux_driver/USB/usb_3100.py
MCC_Linux_driver/USB/usb_ctr.py
MCC_Linux_driver/USB/usb_ctr_rbf.py
MCC_Linux_driver/USB/usb_dio32HS.py
MCC_Linux_driver/USB/usb_dio32HS_rbf.py
MCC_Linux_driver/USB/usb_dioLS.py
MCC_Linux_driver/USB/usb_dioSS.py
MCC_Linux_driver/USB/usb_temp.py
MCC_Linux_driver-0.1.6.dist-info/METADATA
MCC_Linux_driver-0.1.6.dist-info/WHEEL
MCC_Linux_driver-0.1.6.dist-info/top_level.txt
MCC_Linux_driver-0.1.6.dist-info/RECORD
